[
  {
    "name": "Paarivendhar T R",
    "age": "77",
    "party": "DMK",
    "criminal": "2",
    "education": "Post Graduate",
    "assets": 972730368,
    "liabilities": 65935070
  },
  {
    "name": "Anandraj, B.",
    "age": "27",
    "party": "IND",
    "criminal": "0",
    "education": "Others",
    "assets": 4186115,
    "liabilities": 0
  },
  {
    "name": "Annadurai, V.",
    "age": "37",
    "party": "IND",
    "criminal": "0",
    "education": "Post Graduate",
    "assets": 1532000,
    "liabilities": 0
  },
  {
    "name": "Javeed Hussain T",
    "age": "28",
    "party": "IND",
    "criminal": "0",
    "education": "Others",
    "assets": 111000,
    "liabilities": 336000
  },
  {
    "name": "Karuppaiya, M.",
    "age": "34",
    "party": "IND",
    "criminal": "0",
    "education": "10th Pass",
    "assets": 340000,
    "liabilities": 0
  },
  {
    "name": "Murugan, P.",
    "age": "31",
    "party": "IND",
    "criminal": "0",
    "education": "8th Pass",
    "assets": 365000,
    "liabilities": 0
  },
  {
    "name": "Muthulakshmi R",
    "age": "44",
    "party": "BSP",
    "criminal": "0",
    "education": "Post Graduate",
    "assets": 4302000,
    "liabilities": 3300000
  },
  {
    "name": "Pachamuthu, P.",
    "age": "36",
    "party": "IND",
    "criminal": "0",
    "education": "5th Pass",
    "assets": 340000,
    "liabilities": 0
  },
  {
    "name": "Rajasekaran, M.",
    "age": "58",
    "party": "IND",
    "criminal": "5",
    "education": "Post Graduate",
    "assets": 62444127,
    "liabilities": 19100000
  },
  {
    "name": "Rajasekaran, T.",
    "age": "45",
    "party": "IND",
    "criminal": "0",
    "education": "8th Pass",
    "assets": 620000,
    "liabilities": 0
  },
  {
    "name": "Sababathi, S.",
    "age": "26",
    "party": "IND",
    "criminal": "0",
    "education": "Graduate",
    "assets": 280000,
    "liabilities": 0
  },
  {
    "name": "Senthilvel, A.",
    "age": "44",
    "party": "Ulzaipali Makkal Katchy",
    "criminal": "0",
    "education": "10th Pass",
    "assets": 15000,
    "liabilities": 0
  },
  {
    "name": "Shanthi K",
    "age": "36",
    "party": "Naam Tamilar Katchi",
    "criminal": "0",
    "education": "Post Graduate",
    "assets": 311000,
    "liabilities": 0
  },
  {
    "name": "Sivapathy N R",
    "age": "55",
    "party": "AIADMK",
    "criminal": "0",
    "education": "Graduate Professional",
    "assets": 100798649,
    "liabilities": 29580175
  },
  {
    "name": "Suresh, K.",
    "age": "29",
    "party": "IND",
    "criminal": "0",
    "education": "Graduate Professional",
    "assets": 665988,
    "liabilities": 41000
  },
  {
    "name": "Uthamaselvan, N.",
    "age": "47",
    "party": "IND",
    "criminal": "0",
    "education": "Graduate Professional",
    "assets": 251000,
    "liabilities": 0
  },
  {
    "name": "Vincent Melbone, J.",
    "age": "45",
    "party": "IND",
    "criminal": "0",
    "education": "12th Pass",
    "assets": 7581300,
    "liabilities": 0
  },
  {
    "name": "Vinothkumar, S.",
    "age": "27",
    "party": "Tamil Nadu Ilangyar Katchi",
    "criminal": "0",
    "education": "Graduate Professional",
    "assets": 55169,
    "liabilities": 974442
  }
]