[
  {
    "name": "Sumathy Alias Thamizhachi Thangapandian",
    "age": "56",
    "party": "DMK",
    "criminal": "0",
    "education": "Doctorate",
    "assets": 91793460,
    "liabilities": 500000
  },
  {
    "name": "A.J.Sherine",
    "age": "26",
    "party": "Naam Tamilar Katchi",
    "criminal": "0",
    "education": "Post Graduate",
    "assets": 3466760,
    "liabilities": 0
  },
  {
    "name": "A.Naresh",
    "age": "29",
    "party": "Tamil Nadu Ilangyar Katchi",
    "criminal": "0",
    "education": "Graduate Professional",
    "assets": 240000,
    "liabilities": 14000
  },
  {
    "name": "Agni Sriramachandran",
    "age": "38",
    "party": "IND",
    "criminal": "0",
    "education": "10th Pass",
    "assets": 3000000,
    "liabilities": 0
  },
  {
    "name": "B.Raji",
    "age": "28",
    "party": "IND",
    "criminal": "0",
    "education": "Graduate Professional",
    "assets": 30200,
    "liabilities": 0
  },
  {
    "name": "C.Rosi",
    "age": "29",
    "party": "IND",
    "criminal": "0",
    "education": "12th Pass",
    "assets": 2023,
    "liabilities": 0
  },
  {
    "name": "D.Hariharan",
    "age": "44",
    "party": "IND",
    "criminal": "0",
    "education": "Others",
    "assets": 74482760,
    "liabilities": 16000000
  },
  {
    "name": "D.Karthick",
    "age": "33",
    "party": "IND",
    "criminal": "0",
    "education": "Graduate Professional",
    "assets": 579500,
    "liabilities": 0
  },
  {
    "name": "E.Dhanasekaran",
    "age": "51",
    "party": "IND",
    "criminal": "0",
    "education": "10th Pass",
    "assets": 507058,
    "liabilities": 0
  },
  {
    "name": "E.Subaya",
    "age": "55",
    "party": "IND",
    "criminal": "0",
    "education": "Doctorate",
    "assets": 2375841961,
    "liabilities": 18087123
  },
  {
    "name": "G.Devashagayam",
    "age": "40",
    "party": "IND",
    "criminal": "0",
    "education": "Post Graduate",
    "assets": 15460579,
    "liabilities": 9500000
  },
  {
    "name": "G.Dhanasekaran",
    "age": "48",
    "party": "IND",
    "criminal": "0",
    "education": "Graduate Professional",
    "assets": 6896493,
    "liabilities": 0
  },
  {
    "name": "I.Chidambara Anantha Raja",
    "age": "35",
    "party": "IND",
    "criminal": "0",
    "education": "Graduate Professional",
    "assets": 72183,
    "liabilities": 146223
  },
  {
    "name": "J.Jayavardhan",
    "age": "31",
    "party": "AIADMK",
    "criminal": "0",
    "education": "Graduate Professional",
    "assets": 32896587,
    "liabilities": 9621000
  },
  {
    "name": "J.Sibi Chakkaravarthy",
    "age": "54",
    "party": "IND",
    "criminal": "0",
    "education": "Graduate Professional",
    "assets": 833153,
    "liabilities": 470000
  },
  {
    "name": "Janci.J",
    "age": "36",
    "party": "IND",
    "criminal": "1",
    "education": "Graduate",
    "assets": 373500,
    "liabilities": 0
  },
  {
    "name": "K.Jayaraman",
    "age": "43",
    "party": "IND",
    "criminal": "0",
    "education": "12th Pass",
    "assets": 14925696,
    "liabilities": 2053100
  },
  {
    "name": "K.Kannan",
    "age": "46",
    "party": "IND",
    "criminal": "0",
    "education": "Graduate",
    "assets": 249500,
    "liabilities": 0
  },
  {
    "name": "K.Murali Krishnan",
    "age": "69",
    "party": "Pyramid Party of India",
    "criminal": "0",
    "education": "Graduate",
    "assets": 48290000,
    "liabilities": 0
  },
  {
    "name": "K.Saravana Perumal",
    "age": "33",
    "party": "IND",
    "criminal": "0",
    "education": "Graduate",
    "assets": 249000,
    "liabilities": 0
  },
  {
    "name": "K.Sudhakar",
    "age": "50",
    "party": "IND",
    "criminal": "0",
    "education": "5th Pass",
    "assets": 81000,
    "liabilities": 0
  },
  {
    "name": "Kuppal.G.Devadoss",
    "age": "64",
    "party": "IND",
    "criminal": "0",
    "education": "8th Pass",
    "assets": 15731500,
    "liabilities": 6800000
  },
  {
    "name": "M.A.Jeyakumar",
    "age": "64",
    "party": "Desiya Makkal Sakthi Katchi",
    "criminal": "0",
    "education": "10th Pass",
    "assets": 35000,
    "liabilities": 0
  },
  {
    "name": "M.Moorthy",
    "age": "56",
    "party": "IND",
    "criminal": "0",
    "education": "8th Pass",
    "assets": 85342,
    "liabilities": 0
  },
  {
    "name": "M.Rajeswari Priya",
    "age": "36",
    "party": "IND",
    "criminal": "0",
    "education": "Graduate",
    "assets": 12164895,
    "liabilities": 7432748
  },
  {
    "name": "M.Ramanujam Alias M.Radha",
    "age": "53",
    "party": "IND",
    "criminal": "0",
    "education": "12th Pass",
    "assets": 50000,
    "liabilities": 0
  },
  {
    "name": "N.Subramani",
    "age": "49",
    "party": "IND",
    "criminal": "0",
    "education": "Post Graduate",
    "assets": 8217865,
    "liabilities": 200100
  },
  {
    "name": "P.Azhagiri",
    "age": "45",
    "party": "IND",
    "criminal": "0",
    "education": "Graduate Professional",
    "assets": 951363,
    "liabilities": 0
  },
  {
    "name": "P.Karthikeyan",
    "age": "43",
    "party": "IND",
    "criminal": "0",
    "education": "Graduate",
    "assets": 380407,
    "liabilities": 0
  },
  {
    "name": "R.Ganesan",
    "age": "51",
    "party": "IND",
    "criminal": "0",
    "education": "Graduate Professional",
    "assets": 5785732,
    "liabilities": 818474
  },
  {
    "name": "R.Johnson",
    "age": "37",
    "party": "Indian Christian Front",
    "criminal": "2",
    "education": "10th Pass",
    "assets": 1595871,
    "liabilities": 189353
  },
  {
    "name": "R.Kumar",
    "age": "38",
    "party": "BSP",
    "criminal": "0",
    "education": "Graduate",
    "assets": 21000,
    "liabilities": 0
  },
  {
    "name": "R.Rangarajan",
    "age": "40",
    "party": "Makkal Needhi Maiam",
    "criminal": "0",
    "education": "Graduate",
    "assets": 22654934,
    "liabilities": 689310
  },
  {
    "name": "S.Ashok",
    "age": "47",
    "party": "IND",
    "criminal": "0",
    "education": "Graduate Professional",
    "assets": 1251529,
    "liabilities": 0
  },
  {
    "name": "S.Elankumaran",
    "age": "49",
    "party": "IND",
    "criminal": "0",
    "education": "Graduate Professional",
    "assets": 349250,
    "liabilities": 0
  },
  {
    "name": "S.Manova",
    "age": "28",
    "party": "IND",
    "criminal": "0",
    "education": "Graduate Professional",
    "assets": 114029,
    "liabilities": 0
  },
  {
    "name": "S.Srinivasan",
    "age": "57",
    "party": "RPI",
    "criminal": "1",
    "education": "10th Pass",
    "assets": 200912500,
    "liabilities": 0
  },
  {
    "name": "Saikumar.S",
    "age": "53",
    "party": "SUCI(C)",
    "criminal": "0",
    "education": "12th Pass",
    "assets": 1000,
    "liabilities": 0
  },
  {
    "name": "V.Thirunavukkarasu",
    "age": "42",
    "party": "Makkalatchi Katchi",
    "criminal": "0",
    "education": "10th Pass",
    "assets": 480924,
    "liabilities": 230000
  }
]